nasdaq/__init__.py
nasdaq/cli.py
nasdaq/data_processing.py
nasdaq/nasdaq_data_ingestor.py
nasdaq/config/__init__.py
nasdaq/config/settings.py
nasdaq/core/__init__.py
nasdaq/core/base_fetcher.py
nasdaq/core/cookie_manager.py
nasdaq/core/utils.py
nasdaq/fetchers/__init__.py
nasdaq/fetchers/financial.py
nasdaq/fetchers/market.py
nasdaq/fetchers/ownership.py
nasdaq/fetchers/regulatory.py
nasdaq/models/__init__.py
nasdaq/models/base.py
nasdaq/models/company.py
nasdaq/models/financial.py
nasdaq/models/market.py
nasdaq/models/news.py
nasdaq/models/ownership.py
nasdaq/models/regulatory.py
nasdaq_public_api-0.2.0.dist-info/METADATA
nasdaq_public_api-0.2.0.dist-info/WHEEL
nasdaq_public_api-0.2.0.dist-info/entry_points.txt
nasdaq_public_api-0.2.0.dist-info/licenses/LICENSE
nasdaq_public_api-0.2.0.dist-info/RECORD
