Metadata-Version: 2.4
Name: nasdaq-public-api
Version: 0.2.0
Summary: Minimal Nasdaq public API client for accessing market data. Automates cookie management and data retrieval.
Project-URL: Homepage, https://github.com/r-bit-rry/nasdaq-public-api
Project-URL: Repository, https://github.com/r-bit-rry/nasdaq-public-api
Project-URL: Issues, https://github.com/r-bit-rry/nasdaq-public-api/issues
Author-email: r-bit-rry <34023431+r-bit-rry@users.noreply.github.com>
License: MIT License
License-File: LICENSE
Keywords: api-client,finance,market-data,nasdaq,stocks
Classifier: Development Status :: 3 - Alpha
Classifier: Intended Audience :: Developers
Classifier: Intended Audience :: Financial and Insurance Industry
Classifier: License :: OSI Approved :: MIT License
Classifier: Programming Language :: Python :: 3
Classifier: Programming Language :: Python :: 3.12
Classifier: Topic :: Office/Business :: Financial :: Investment
Classifier: Topic :: Software Development :: Libraries :: Python Modules
Requires-Python: >=3.12
Requires-Dist: pandas
Requires-Dist: requests
Requires-Dist: selenium
Provides-Extra: dev
Requires-Dist: black>=25.1.0; extra == 'dev'
Requires-Dist: pyan3>=1.2.0; extra == 'dev'
Requires-Dist: pylint-mccabe>=0.1.3; extra == 'dev'
Requires-Dist: pylint-pydantic>=0.3.5; extra == 'dev'
Requires-Dist: pylint>=3.3.7; extra == 'dev'
Requires-Dist: pytest; extra == 'dev'
Requires-Dist: radon>=6.0.1; extra == 'dev'
Requires-Dist: ruff>=0.12.7; extra == 'dev'
Requires-Dist: vulture>=2.14; extra == 'dev'
